linguado/__init__.py
linguado/ast_generator.py
linguado/graph_calculations.py
linguado/linguado.py
linguado/sample.py
linguado/sample_generator.py
linguado/weisfeiler_lehman.py
linguado/writer.py
linguado/c/CLexer.py
linguado/c/CListener.py
linguado/c/CParser.py
linguado/javascript/JavaScriptLexer.py
linguado/javascript/JavaScriptLexerBase.py
linguado/javascript/JavaScriptParser.py
linguado/javascript/JavaScriptParserBase.py
linguado/javascript/JavaScriptParserListener.py
linguado/javascript/__init__.py
linguado/javascript/transformGrammar.py
linguado/nasm_x86_64/nasm_x86_64_Lexer.py
linguado/nasm_x86_64/nasm_x86_64_Parser.py
linguado/nasm_x86_64/nasm_x86_64_ParserListener.py
linguado/php/PhpLexer.py
linguado/php/PhpLexerBase.py
linguado/php/PhpParser.py
linguado/php/PhpParserListener.py
linguado/php/__init__.py
linguado/php/transformGrammar.py
linguado/python2/Python2Lexer.py
linguado/python2/Python2Listener.py
linguado/python2/Python2Parser.py
linguado/python2/__init__.py
linguado/python3/Python3Lexer.py
linguado/python3/Python3LexerBase.py
linguado/python3/Python3Parser.py
linguado/python3/Python3ParserBase.py
linguado/python3/Python3ParserListener.py
linguado/python3/__init__.py
linguado/python3/transformGrammar.py
linguado/vba/__init__.py
linguado/vba/vbaLexer.py
linguado/vba/vbaListener.py
linguado/vba/vbaParser.py
linguado-0.2.0.dist-info/LICENSE
linguado-0.2.0.dist-info/METADATA
linguado-0.2.0.dist-info/WHEEL
linguado-0.2.0.dist-info/entry_points.txt
linguado-0.2.0.dist-info/top_level.txt
linguado-0.2.0.dist-info/RECORD
