Metadata-Version: 2.1
Name: linguado
Version: 0.2.0
Summary: Linguado is a tool which compares the AST of two or more files
Author-email: Guzmán Cernadas Pérez <guzman.cernadas@protonmail.com>
Maintainer-email: Guzmán Cernadas Pérez <guzman.cernadas@protonmail.com>
License: GNU GENERAL PUBLIC LICENSE
Project-URL: repository, https://github.com/Caralludo/linguado.git
Keywords: AST,compare
Classifier: Programming Language :: Python :: 3
Classifier: License :: OSI Approved :: GNU General Public License v3 (GPLv3)
Requires-Python: >=3.8
License-File: LICENSE
Requires-Dist: numpy
Requires-Dist: tqdm
Requires-Dist: igraph
Requires-Dist: networkx
Requires-Dist: antlr4-python3-runtime
Requires-Dist: setuptools
